App/__init__.py
App/app.py
App/app_instance.py
App/assets/MS2LDA_LOGO_black.jpg
App/assets/MS2LDA_LOGO_white.jpg
App/assets/WUR_RGB_standard_2021.png
App/assets/favicon.ico
App/callbacks/__init__.py
App/callbacks/common.py
App/callbacks/network.py
App/callbacks/rankings_details.py
App/callbacks/run_and_load.py
App/callbacks/screening.py
App/layout/__init__.py
App/layout/load_results.py
App/layout/motif_details.py
App/layout/motif_rankings.py
App/layout/motif_search.py
App/layout/network_view.py
App/layout/run_analysis.py
App/layout/spectra_search.py
MS2LDA/.ipynb_checkpoints/MS2LDA_core-checkpoint.py
MS2LDA/Add_On/Fingerprints/FP_annotation.py
MS2LDA/Add_On/Fingerprints/FP_calculation/README.md
MS2LDA/Add_On/Fingerprints/FP_calculation/adaptive_fps.py
MS2LDA/Add_On/Fingerprints/FP_calculation/cdk_fps.py
MS2LDA/Add_On/Fingerprints/FP_calculation/jmap_fps.py
MS2LDA/Add_On/Fingerprints/FP_calculation/map4.py
MS2LDA/Add_On/Fingerprints/FP_calculation/mhfp.py
MS2LDA/Add_On/Fingerprints/FP_calculation/minhash_fps.py
MS2LDA/Add_On/Fingerprints/FP_calculation/rdkit_fps.py
MS2LDA/Add_On/Fingerprints/Substructure_retrieval.py
MS2LDA/Add_On/Fingerprints/__init__.py
MS2LDA/Add_On/Fingerprints/__version__.py
MS2LDA/Add_On/MassQL/MassQL4MotifDB.py
MS2LDA/Add_On/MassQL/__init__.py
MS2LDA/Add_On/NTS/Screening.py
MS2LDA/Add_On/NTS/__init__.py
MS2LDA/Add_On/Spec2Vec/__init__.py
MS2LDA/Add_On/Spec2Vec/annotation.py
MS2LDA/Add_On/Spec2Vec/annotation_refined.py
MS2LDA/Add_On/__init__.py
MS2LDA/Mass2Motif.py
MS2LDA/Mass2MotifDocument.py
MS2LDA/Preprocessing/__init__.py
MS2LDA/Preprocessing/generate_corpus.py
MS2LDA/Preprocessing/load_and_clean.py
MS2LDA/Visualisation/MS2LDA_visualisation.py
MS2LDA/Visualisation/__init__.py
MS2LDA/Visualisation/ldadict.py
MS2LDA/Visualisation/plot_MotifsetSimilarity.py
MS2LDA/Visualisation/visualisation.py
MS2LDA/__init__.py
MS2LDA/__version__.py
MS2LDA/modeling.py
MS2LDA/motif_parser.py
MS2LDA/run.py
MS2LDA/utils.py
massql4motifs/README.included.md
ms2lda-2.0.1.dist-info/LICENSE
ms2lda-2.0.1.dist-info/METADATA
ms2lda-2.0.1.dist-info/WHEEL
ms2lda-2.0.1.dist-info/entry_points.txt
ms2lda-2.0.1.dist-info/RECORD
