Metadata-Version: 2.3
Name: ms2lda
Version: 2.0.1
Summary: Unsupervised Substructure Discovery using Topic Modelling with Automated Annotation.
License: MIT
Keywords: mass spectrometry,metabolomics,topic modeling,LDA,substructure discovery,cheminformatics
Author: MS2LDA Development Team
Author-email: justin.vanderhooft@wur.nl
Maintainer: MS2LDA Development Team
Maintainer-email: justin.vanderhooft@wur.nl
Requires-Python: >=3.11,<3.13
Classifier: Development Status :: 5 - Production/Stable
Classifier: Environment :: Console
Classifier: Environment :: Web Environment
Classifier: Intended Audience :: Science/Research
Classifier: License :: OSI Approved :: MIT License
Classifier: Operating System :: OS Independent
Classifier: Programming Language :: Python :: 3
Classifier: Programming Language :: Python :: 3.11
Classifier: Programming Language :: Python :: 3.12
Classifier: Topic :: Scientific/Engineering :: Bio-Informatics
Classifier: Topic :: Scientific/Engineering :: Chemistry
Provides-Extra: lite
Provides-Extra: notebook
Requires-Dist: PyQt6 (>=6.7.1,<7.0.0)
Requires-Dist: dash (>=2.18.1,<3.0.0)
Requires-Dist: dash-bootstrap-components (>=1.6.0,<2.0.0)
Requires-Dist: dash-cytoscape (>=1.0.2,<2.0.0)
Requires-Dist: dash-extensions (==1.0.20)
Requires-Dist: diskcache (>=5.6.3)
Requires-Dist: faiss-cpu (==1.10.0)
Requires-Dist: gensim (>=4.3.3,<5.0.0)
Requires-Dist: ipython (>=8.26.0,<9.0.0) ; extra == "notebook"
Requires-Dist: jupyterlab (>=4.2.4,<5.0.0) ; extra == "notebook"
Requires-Dist: kaleido (==0.2.1) ; extra == "notebook"
Requires-Dist: lark-parser (>=0.12.0,<0.13.0)
Requires-Dist: matchms (>=0.27,<1)
Requires-Dist: matplotlib (>=3.9.1,<4.0.0)
Requires-Dist: networkx (>=3.3,<4.0)
Requires-Dist: openpyxl (==3.1.5)
Requires-Dist: pandas (>=2.2.2,<3.0.0)
Requires-Dist: plotly (>=5.23.0,<6.0.0)
Requires-Dist: psims (>=1.3.3,<2.0.0)
Requires-Dist: pubchempy (>=1.0.4,<2.0.0)
Requires-Dist: py_expression_eval (>=0.3.0,<0.4.0)
Requires-Dist: pyarrow (>=17.0.0,<18.0.0)
Requires-Dist: pydot (>=3.0.0,<4.0.0)
Requires-Dist: pymzml (>=2.5.10,<3.0.0)
Requires-Dist: pyyaml (>=6.0.2,<7.0.0)
Requires-Dist: rdkit (>=2023.9.6,<2026)
Requires-Dist: requests (>=2.32.3,<3.0.0)
Requires-Dist: scikit-learn (>=1.5.1,<2.0.0)
Requires-Dist: scipy (>=1.10.1,<2.0.0)
Requires-Dist: seaborn (>=0.13.2,<0.14.0)
Requires-Dist: spec2vec (>=0.8.0,<0.9.0)
Requires-Dist: tomotopy (>=0.12.7)
Project-URL: Documentation, https://ms2lda.org
Project-URL: Homepage, https://github.com/vdhooftcompmet/MS2LDA
Project-URL: Repository, https://github.com/vdhooftcompmet/MS2LDA
